{
  "_class" : "hudson.plugins.git.util.BuildData",
  "buildsByBranchName" : {
    "provision/6.x-2.x" : {
      "_class" : "hudson.plugins.git.util.Build",
      "buildNumber" : 16,
      "buildResult" : null,
      "marked" : {
        "SHA1" : "15d5e0e5ff3757a01604d9d00c4d571bedf98656",
        "branch" : [
          {
            "SHA1" : "15d5e0e5ff3757a01604d9d00c4d571bedf98656",
            "name" : "provision/6.x-2.x"
          }
        ]
      },
      "revision" : {
        "SHA1" : "15d5e0e5ff3757a01604d9d00c4d571bedf98656",
        "branch" : [
          {
            "SHA1" : "15d5e0e5ff3757a01604d9d00c4d571bedf98656",
            "name" : "provision/6.x-2.x"
          }
        ]
      }
    }
  },
  "lastBuiltRevision" : {
    "SHA1" : "15d5e0e5ff3757a01604d9d00c4d571bedf98656",
    "branch" : [
      {
        "SHA1" : "15d5e0e5ff3757a01604d9d00c4d571bedf98656",
        "name" : "provision/6.x-2.x"
      }
    ]
  },
  "remoteUrls" : [
    
  ],
  "scmName" : ""
}